[
  [
    {
      "email": "1",
      "password": "1"
    },
    {
      "email": "test@gmail.com",
      "password": "password"
    },
    {
      "email": "123",
      "password": "123"
    },
    {
      "email": "1234",
      "password": "1234"
    },
    {
      "email": "FakeEmail@gmail.com",
      "password": "Password123"
    }
  ],
  [
    {
      "name": "Apple Inc.",
      "ticker": "AAPL",
      "peRatio": "29.5",
      "logoUrl": "https://encrypted-tbn0.gstatic.com/images?q=tbn:ANd9GcRCvh-j7HsTHJ8ZckknAoiZMx9VcFmsFkv72g&s",
      "comments": [
        {
          "userEmail": "example.domain.com",
          "UserComment": "I Like apple but not at these lofty valuations"
        },
        {
          "userEmail": "example2.domain.com",
          "UserComment": "IM SELLING"
        }
      ]
    },
    {
      "name": "Microsoft Corp.",
      "ticker": "MSFT",
      "marketCap": "2.5T",
      "peRatio": "34.6",
      "logoUrl": "https://cdn-dynmedia-1.microsoft.com/is/image/microsoftcorp/RWCZER-Legal-IP-Trademarks-CP-MS-logo-740x417-1?wid=406&hei=230&fit=crop"
    },
    {
      "name": "Alphabet Inc. (Google)",
      "ticker": "GOOGL",
      "marketCap": "1.8T",
      "peRatio": "25.2",
      "logoUrl": "https://53.fs1.hubspotusercontent-na1.net/hubfs/53/image8-2.jpg"
    },
    {
      "name": "Amazon.com Inc.",
      "ticker": "AMZN",
      "marketCap": "1.6T",
      "peRatio": "59.5",
      "logoUrl": "https://upload.wikimedia.org/wikipedia/commons/a/a9/Amazon_logo.svg"
    },
    {
      "name": "Tesla Inc.",
      "ticker": "TSLA",
      "marketCap": "850B",
      "peRatio": "82.3",
      "logoUrl": "https://upload.wikimedia.org/wikipedia/commons/e/e8/Tesla_logo.png"
    }
  ]
]
